Metadata-Version: 1.2
Name: youscan
Version: 0.0.1
Summary: Youscan Insight Rest Api wrapper
Home-page: https://github.com/bzdvdn/youscan-wrapper.git
Author: bzdvdn
Author-email: bzdv.dn@gmail.com
License: MIT
Platform: UNKNOWN
Requires-Python: >=3.6
